{"data":[{"ast":3,"blk":0,"dreb":2,"fg3_pct":0.0,"fg3a":5,"fg3m":0,"fg_pct":0.2,"fga":10,"fgm":2,"fta":0,"ftm":0,"game":{"date":"2021-11-16T00:00:00.000Z","home_team_id":13,"home_team_score":106,"id":473619,"period":4,"postseason":false,"season":2021,"status":"Final","time":"","visitor_team_id":27,"visitor_team_score":92},"id":8113281,"min":"19","oreb":0,"pf":2,"player":{"first_name":"Lonnie","height_feet":6,"height_inches":5,"id":464,"last_name":"Walker IV","position":"G","team_id":14,"weight_pounds":205},"pts":4,"reb":2,"stl":0,"team":{"abbreviation":"SAS","city":"San Antonio","conference":"West","division":"Southwest","full_name":"San Antonio Spurs","id":27,"name":"Spurs"},"turnover":1},{"ast":0,"blk":1,"dreb":0,"fg3_pct":0.0,"fg3a":1,"fg3m":0,"fg_pct":0.0,"fga":3,"fgm":0,"ft_pct":0.0,"fta":0,"ftm":0,"game":{"date":"2021-11-16T00:00:00.000Z","home_team_id":13,"home_team_score":106,"id":473619,"period":4,"postseason":false,"season":2021,"status":"Final","time":"","visitor_team_id":27,"visitor_team_score":92},"id":8113278,"min":"12:13","oreb":0,"pf":1,"player":{"first_name":"Bryn","height_feet":6,"height_inches":3,"id":159,"last_name":"Forbes","position":"G","team_id":18,"weight_pounds":190},"pts":0,"reb":0,"stl":0,"team":{"abbreviation":"SAS","city":"San Antonio","conference":"West","division":"Southwest","full_name":"San Antonio Spurs","id":27,"name":"Spurs"},"turnover":0},{"ast":0,"blk":0,"dreb":0,"fg3_pct":0.0,"fg3a":1,"fg3m":0,"fg_pct":0.5,"fga":6,"fgm":3,"fta":0,"ftm":0,"game":{"date":"2021-11-16T00:00:00.000Z","home_team_id":13,"home_team_score":106,"id":473619,"period":4,"postseason":false,"season":2021,"status":"Final","time":"","visitor_team_id":27,"visitor_team_score":92},"id":8113279,"min":"9","oreb":1,"pf":1,"player":{"first_name":"Tre","id":3547274,"last_name":"Jones","position":"G","team_id":27},"pts":6,"reb":1,"stl":1,"team":{"abbreviation":"SAS","city":"San Antonio","conference":"West","division":"Southwest","full_name":"San Antonio Spurs","id":27,"name":"Spurs"},"turnover":0},{"ast":0,"blk":0,"dreb":0,"fg3_pct":0.0,"fg3a":0,"fg3m":0,"fg_pct":0.0,"fga":0,"fgm":0,"ft_pct":0.0,"fta":0,"ftm":0,"game":{"date":"2021-11-16T00:00:00.000Z","home_team_id":13,"home_team_score":106,"id":473619,"period":4,"postseason":false,"season":2021,"status":"Final","time":"","visitor_team_id":27,"visitor_team_score":92},"id":8113277,"min":"0:00","oreb":0,"pf":0,"player":{"first_name":"Keita","height_feet":6,"height_inches":9,"id":32,"last_name":"Bates-Diop","position":"F","team_id":27,"weight_pounds":229},"pts":0,"reb":0,"stl":0,"team":{"abbreviation":"SAS","city":"San Antonio","conference":"West","division":"Southwest","full_name":"San Antonio Spurs","id":27,"name":"Spurs"},"turnover":0},{"ast":3,"blk":1,"dreb":4,"fg3_pct":0.5,"fg3a":4,"fg3m":2,"fg_pct":0.444,"fga":9,"fgm":4,"fta":0,"ftm":0,"game":{"date":"2021-11-16T00:00:00.000Z","home_team_id":13,"home_team_score":106,"id":473619,"period":4,"postseason":false,"season":2021,"status":"Final","time":"","visitor_team_id":27,"visitor_team_score":92},"id":8113272,"min":"33","oreb":1,"pf":2,"player":{"first_name":"Keldon","id":666682,"last_name":"Johnson","position":"F","team_id":27},"pts":10,"reb":5,"stl":1,"team":{"abbreviation":"SAS","city":"San Antonio","conference":"West","division":"Southwest","full_name":"San Antonio Spurs","id":27,"name":"Spurs"},"turnover":3},{"ast":2,"blk":0,"dreb":2,"fg3_pct":0.25,"fg3a":4,"fg3m":1,"fg_pct":0.3,"fga":10,"fgm":3,"fta":0,"ftm":0,"game":{"date":"2021-11-16T00:00:00.000Z","home_team_id":13,"home_team_score":106,"id":473619,"period":4,"postseason":false,"season":2021,"status":"Final","time":"","visitor_team_id":27,"visitor_team_score":92},"id":8113273,"min":"29","oreb":1,"pf":0,"player":{"first_name":"Doug","height_feet":6,"height_inches":8,"id":305,"last_name":"McDermott","position":"F","team_id":27,"weight_pounds":225},"pts":7,"reb":3,"stl":1,"team":{"abbreviation":"SAS","city":"San Antonio","conference":"West","division":"Southwest","full_name":"San Antonio Spurs","id":27,"name":"Spurs"},"turnover":1},{"ast":1,"blk":1,"dreb":10,"fg3a":0,"fg3m":0,"fg_pct":0.429,"fga":7,"fgm":3,"ft_pct":1.0,"fta":2,"ftm":2,"game":{"date":"2021-11-16T00:00:00.000Z","home_team_id":13,"home_team_score":106,"id":473619,"period":4,"postseason":false,"season":2021,"status":"Final","time":"","visitor_team_id":27,"visitor_team_score":92},"id":8113274,"min":"24","oreb":0,"pf":3,"player":{"first_name":"Drew","height_feet":6,"height_inches":10,"id":147,"last_name":"Eubanks","position":"F","team_id":25,"weight_pounds":245},"pts":8,"reb":10,"stl":0,"team":{"abbreviation":"SAS","city":"San Antonio","conference":"West","division":"Southwest","full_name":"San Antonio Spurs","id":27,"name":"Spurs"},"turnover":1},{"ast":9,"blk":0,"dreb":10,"fg3_pct":0.5,"fg3a":2,"fg3m":1,"fg_pct":0.571,"fga":21,"fgm":12,"ft_pct":0.5,"fta":2,"ftm":1,"game":{"date":"2021-11-16T00:00:00.000Z","home_team_id":13,"home_team_score":106,"id":473619,"period":4,"postseason":false,"season":2021,"status":"Final","time":"","visitor_team_id":27,"visitor_team_score":92},"id":8113275,"min":"39","oreb":2,"pf":1,"player":{"first_name":"Dejounte","height_feet":6,"height_inches":5,"id":334,"last_name":"Murray","position":"G","team_id":1,"weight_pounds":170},"pts":26,"reb":12,"stl":3,"team":{"abbreviation":"SAS","city":"San Antonio","conference":"West","division":"Southwest","full_name":"San Antonio Spurs","id":27,"name":"Spurs"},"turnover":4},{"ast":3,"blk":0,"dreb":3,"fg3_pct":0.25,"fg3a":4,"fg3m":1,"fg_pct":0.571,"fga":14,"fgm":8,"ft_pct":1.0,"fta":2,"ftm":2,"game":{"date":"2021-11-16T00:00:00.000Z","home_team_id":13,"home_team_score":106,"id":473619,"period":4,"postseason":false,"season":2021,"status":"Final","time":"","visitor_team_id":27,"visitor_team_score":92},"id":8113276,"min":"32","oreb":0,"pf":4,"player":{"first_name":"Derrick","height_feet":6,"height_inches":4,"id":473,"last_name":"White","position":"G","team_id":2,"weight_pounds":190},"pts":19,"reb":3,"stl":1,"team":{"abbreviation":"SAS","city":"San Antonio","conference":"West","division":"Southwest","full_name":"San Antonio Spurs","id":27,"name":"Spurs"},"turnover":3},{"ast":0,"blk":1,"dreb":1,"fg3_pct":0.0,"fg3a":1,"fg3m":0,"fg_pct":0.25,"fga":4,"fgm":1,"fta":0,"ftm":0,"game":{"date":"2021-11-16T00:00:00.000Z","home_team_id":13,"home_team_score":106,"id":473619,"period":4,"postseason":false,"season":2021,"status":"Final","time":"","visitor_team_id":27,"visitor_team_score":92},"id":8113280,"min":"19","oreb":0,"pf":1,"player":{"first_name":"Devin","id":3547246,"last_name":"Vassell","position":"G-F","team_id":27},"pts":2,"reb":1,"stl":1,"team":{"abbreviation":"SAS","city":"San Antonio","conference":"West","division":"Southwest","full_name":"San Antonio Spurs","id":27,"name":"Spurs"},"turnover":0},{"ast":5,"blk":0,"dreb":3,"fg3a":0,"fg3m":0,"fg_pct":0.455,"fga":11,"fgm":5,"ft_pct":0.0,"fta":1,"ftm":0,"game":{"date":"2021-11-16T00:00:00.000Z","home_team_id":13,"home_team_score":106,"id":473619,"period":4,"postseason":false,"season":2021,"status":"Final","time":"","visitor_team_id":27,"visitor_team_score":92},"id":8113282,"min":"24","oreb":1,"pf":2,"player":{"first_name":"Thaddeus","height_feet":6,"height_inches":8,"id":489,"last_name":"Young","position":"F","team_id":28,"weight_pounds":221},"pts":10,"reb":4,"stl":2,"team":{"abbreviation":"SAS","city":"San Antonio","conference":"West","division":"Southwest","full_name":"San Antonio Spurs","id":27,"name":"Spurs"},"turnover":3},{"ast":4,"blk":0,"dreb":9,"fg3_pct":0.222,"fg3a":9,"fg3m":2,"fg_pct":0.417,"fga":24,"fgm":10,"ft_pct":0.923,"fta":13,"ftm":12,"game":{"date":"2021-11-16T00:00:00.000Z","home_team_id":13,"home_team_score":106,"id":473619,"period":4,"postseason":false,"season":2021,"status":"Final","time":"","visitor_team_id":27,"visitor_team_score":92},"id":8113283,"min":"34","oreb":0,"pf":1,"player":{"first_name":"Paul","height_feet":6,"height_inches":9,"id":172,"last_name":"George","position":"F","team_id":13,"weight_pounds":220},"pts":34,"reb":9,"stl":2,"team":{"abbreviation":"LAC","city":"LA","conference":"West","division":"Pacific","full_name":"LA Clippers","id":13,"name":"Clippers"},"turnover":6},{"ast":2,"blk":0,"dreb":1,"fg3_pct":0.0,"fg3a":1,"fg3m":0,"fg_pct":0.0,"fga":1,"fgm":0,"ft_pct":0.0,"fta":0,"ftm":0,"game":{"date":"2021-11-16T00:00:00.000Z","home_team_id":13,"home_team_score":106,"id":473619,"period":4,"postseason":false,"season":2021,"status":"Final","time":"","visitor_team_id":27,"visitor_team_score":92},"id":8113284,"min":"13:56","oreb":0,"pf":0,"player":{"first_name":"Nicolas","height_feet":6,"height_inches":8,"id":33,"last_name":"Batum","position":"F-G","team_id":13,"weight_pounds":200},"pts":0,"reb":1,"stl":0,"team":{"abbreviation":"LAC","city":"LA","conference":"West","division":"Pacific","full_name":"LA Clippers","id":13,"name":"Clippers"},"turnover":0},{"ast":1,"blk":0,"dreb":7,"fg3a":0,"fg3m":0,"fg_pct":0.429,"fga":7,"fgm":3,"ft_pct":1.0,"fta":2,"ftm":2,"game":{"date":"2021-11-16T00:00:00.000Z","home_team_id":13,"home_team_score":106,"id":473619,"period":4,"postseason":false,"season":2021,"status":"Final","time":"","visitor_team_id":27,"visitor_team_score":92},"id":8113285,"min":"31","oreb":6,"pf":2,"player":{"first_name":"Ivica","height_feet":7,"height_inches":1,"id":493,"last_name":"Zubac","position":"C","team_id":13,"weight_pounds":240},"pts":8,"reb":13,"stl":1,"team":{"abbreviation":"LAC","city":"LA","conference":"West","division":"Pacific","full_name":"LA Clippers","id":13,"name":"Clippers"},"turnover":1},{"ast":0,"blk":0,"dreb":6,"fg3_pct":0.333,"fg3a":3,"fg3m":1,"fg_pct":0.417,"fga":12,"fgm":5,"fta":0,"ftm":0,"game":{"date":"2021-11-16T00:00:00.000Z","home_team_id":13,"home_team_score":106,"id":473619,"period":4,"postseason":false,"season":2021,"status":"Final","time":"","visitor_team_id":27,"visitor_team_score":92},"id":8113286,"min":"30","oreb":0,"pf":0,"player":{"first_name":"Eric","height_feet":6,"height_inches":1,"id":51,"last_name":"Bledsoe","position":"G","team_id":25,"weight_pounds":205},"pts":11,"reb":6,"stl":3,"team":{"abbreviation":"LAC","city":"LA","conference":"West","division":"Pacific","full_name":"LA Clippers","id":13,"name":"Clippers"},"turnover":3},{"ast":4,"blk":2,"dreb":6,"fg3_pct":0.294,"fg3a":17,"fg3m":5,"fg_pct":0.364,"fga":22,"fgm":8,"fta":0,"ftm":0,"game":{"date":"2021-11-16T00:00:00.000Z","home_team_id":13,"home_team_score":106,"id":473619,"period":4,"postseason":false,"season":2021,"status":"Final","time":"","visitor_team_id":27,"visitor_team_score":92},"id":8113287,"min":"38","oreb":0,"pf":3,"player":{"first_name":"Reggie","height_feet":6,"height_inches":3,"id":236,"last_name":"Jackson","position":"G","team_id":8,"weight_pounds":208},"pts":21,"reb":6,"stl":0,"team":{"abbreviation":"LAC","city":"LA","conference":"West","division":"Pacific","full_name":"LA Clippers","id":13,"name":"Clippers"},"turnover":3},{"ast":2,"blk":0,"dreb":7,"fg3_pct":1.0,"fg3a":1,"fg3m":1,"fg_pct":0.6,"fga":5,"fgm":3,"fta":0,"ftm":0,"game":{"date":"2021-11-16T00:00:00.000Z","home_team_id":13,"home_team_score":106,"id":473619,"period":4,"postseason":false,"season":2021,"status":"Final","time":"","visitor_team_id":27,"visitor_team_score":92},"id":8113292,"min":"31","oreb":0,"pf":2,"player":{"first_name":"Luke","height_feet":6,"height_inches":5,"id":254,"last_name":"Kennard","position":"G","team_id":15,"weight_pounds":206},"pts":7,"reb":7,"stl":0,"team":{"abbreviation":"LAC","city":"LA","conference":"West","division":"Pacific","full_name":"LA Clippers","id":13,"name":"Clippers"},"turnover":3},{"ast":2,"blk":1,"dreb":2,"fg3_pct":0.333,"fg3a":3,"fg3m":1,"fg_pct":0.333,"fga":3,"fgm":1,"ft_pct":1.0,"fta":2,"ftm":2,"game":{"date":"2021-11-16T00:00:00.000Z","home_team_id":13,"home_team_score":106,"id":473619,"period":4,"postseason":false,"season":2021,"status":"Final","time":"","visitor_team_id":27,"visitor_team_score":92},"id":8113289,"min":"25","oreb":0,"pf":3,"player":{"first_name":"Amir","id":666511,"last_name":"Coffey","position":"G","team_id":13},"pts":5,"reb":2,"stl":0,"team":{"abbreviation":"LAC","city":"LA","conference":"West","division":"Pacific","full_name":"LA Clippers","id":13,"name":"Clippers"},"turnover":0},{"ast":1,"blk":0,"dreb":4,"fg3_pct":0.5,"fg3a":4,"fg3m":2,"fg_pct":0.571,"fga":7,"fgm":4,"ft_pct":1.0,"fta":3,"ftm":3,"game":{"date":"2021-11-16T00:00:00.000Z","home_team_id":13,"home_team_score":106,"id":473619,"period":4,"postseason":false,"season":2021,"status":"Final","time":"","visitor_team_id":27,"visitor_team_score":92},"id":8113288,"min":"20","oreb":0,"pf":0,"player":{"first_name":"Brandon","id":17896022,"last_name":"Boston Jr.","position":"G","team_id":13},"pts":13,"reb":4,"stl":1,"team":{"abbreviation":"LAC","city":"LA","conference":"West","division":"Pacific","full_name":"LA Clippers","id":13,"name":"Clippers"},"turnover":1},{"ast":0,"blk":0,"dreb":4,"fg3a":0,"fg3m":0,"fg_pct":1.0,"fga":3,"fgm":3,"ft_pct":0.5,"fta":2,"ftm":1,"game":{"date":"2021-11-16T00:00:00.000Z","home_team_id":13,"home_team_score":106,"id":473619,"period":4,"postseason":false,"season":2021,"status":"Final","time":"","visitor_team_id":27,"visitor_team_score":92},"id":8113290,"min":"17","oreb":0,"pf":2,"player":{"first_name":"Isaiah","height_feet":7,"height_inches":0,"id":201,"last_name":"Hartenstein","position":"F-C","team_id":20,"weight_pounds":249},"pts":7,"reb":4,"stl":1,"team":{"abbreviation":"LAC","city":"LA","conference":"West","division":"Pacific","full_name":"LA Clippers","id":13,"name":"Clippers"},"turnover":3},{"ast":0,"blk":0,"dreb":0,"fg3_pct":0.0,"fg3a":0,"fg3m":0,"fg_pct":0.0,"fga":1,"fgm":0,"ft_pct":0.0,"fta":0,"ftm":0,"game":{"date":"2021-11-16T00:00:00.000Z","home_team_id":13,"home_team_score":106,"id":473619,"period":4,"postseason":false,"season":2021,"status":"Final","time":"","visitor_team_id":27,"visitor_team_score":92},"id":8113293,"min":"1:05","oreb":0,"pf":0,"player":{"first_name":"Jay","id":3547280,"last_name":"Scrubb","position":"G","team_id":22},"pts":0,"reb":0,"stl":1,"team":{"abbreviation":"LAC","city":"LA","conference":"West","division":"Pacific","full_name":"LA Clippers","id":13,"name":"Clippers"},"turnover":0},{"ast":0,"blk":0,"dreb":0,"fg3_pct":0.0,"fg3a":0,"fg3m":0,"fg_pct":0.0,"fga":0,"fgm":0,"ft_pct":0.0,"fta":0,"ftm":0,"game":{"date":"2021-11-16T00:00:00.000Z","home_team_id":13,"home_team_score":106,"id":473619,"period":4,"postseason":false,"season":2021,"status":"Final","time":"","visitor_team_id":27,"visitor_team_score":92},"id":8113291,"min":"","oreb":0,"pf":0,"player":{"first_name":"Keon","id":17896041,"last_name":"Johnson","position":"G","team_id":25},"pts":0,"reb":0,"stl":0,"team":{"abbreviation":"LAC","city":"LA","conference":"West","division":"Pacific","full_name":"LA Clippers","id":13,"name":"Clippers"},"turnover":0},{"ast":1,"blk":0,"dreb":2,"fg3_pct":0.333,"fg3a":3,"fg3m":1,"fg_pct":0.333,"fga":6,"fgm":2,"ft_pct":1.0,"fta":2,"ftm":2,"game":{"date":"2021-11-21T00:00:00.000Z","home_team_id":13,"home_team_score":97,"id":473658,"period":4,"postseason":false,"season":2021,"status":"Final","time":"","visitor_team_id":7,"visitor_team_score":91},"id":8241214,"min":"24","oreb":0,"pf":3,"player":{"first_name":"Dorian","height_feet":6,"height_inches":8,"id":158,"last_name":"Finney-Smith","position":"F","team_id":3,"weight_pounds":220},"pts":7,"reb":2,"stl":1,"team":{"abbreviation":"DAL","city":"Dallas","conference":"West","division":"Southwest","full_name":"Dallas Mavericks","id":7,"name":"Mavericks"},"turnover":0},{"ast":2,"blk":2,"dreb":4,"fg3_pct":0.0,"fg3a":4,"fg3m":0,"fg_pct":0.556,"fga":18,"fgm":10,"ft_pct":0.833,"fta":6,"ftm":5,"game":{"date":"2021-11-21T00:00:00.000Z","home_team_id":13,"home_team_score":97,"id":473658,"period":4,"postseason":false,"season":2021,"status":"Final","time":"","visitor_team_id":7,"visitor_team_score":91},"id":8241215,"min":"32","oreb":4,"pf":4,"player":{"first_name":"Kristaps","height_feet":7,"height_inches":3,"id":378,"last_name":"Porzingis","position":"F-C","team_id":30,"weight_pounds":240},"pts":25,"reb":8,"stl":0,"team":{"abbreviation":"DAL","city":"Dallas","conference":"West","division":"Southwest","full_name":"Dallas Mavericks","id":7,"name":"Mavericks"},"turnover":0},{"ast":1,"blk":1,"dreb":3,"fg3_pct":0.5,"fg3a":2,"fg3m":1,"fg_pct":0.571,"fga":7,"fgm":4,"fta":0,"ftm":0,"game":{"date":"2021-11-21T00:00:00.000Z","home_team_id":13,"home_team_score":97,"id":473658,"period":4,"postseason":false,"season":2021,"status":"Final","time":"","visitor_team_id":7,"visitor_team_score":91},"id":8241216,"min":"19","oreb":2,"pf":1,"player":{"first_name":"Dwight","height_feet":6,"height_inches":11,"id":379,"last_name":"Powell","position":"F-C","team_id":7,"weight_pounds":240},"pts":9,"reb":5,"stl":0,"team":{"abbreviation":"DAL","city":"Dallas","conference":"West","division":"Southwest","full_name":"Dallas Mavericks","id":7,"name":"Mavericks"},"turnover":1},{"ast":5,"blk":0,"dreb":5,"fg3_pct":0.25,"fg3a":4,"fg3m":1,"fg_pct":0.167,"fga":12,"fgm":2,"ft_pct":1.0,"fta":3,"ftm":3,"game":{"date":"2021-11-21T00:00:00.000Z","home_team_id":13,"home_team_score":97,"id":473658,"period":4,"postseason":false,"season":2021,"status":"Final","time":"","visitor_team_id":7,"visitor_team_score":91},"id":8241217,"min":"36","oreb":1,"pf":4,"player":{"first_name":"Tim","height_feet":6,"height_inches":6,"id":191,"last_name":"Hardaway Jr.","position":"G","team_id":7,"weight_pounds":205},"pts":8,"reb":6,"stl":0,"team":{"abbreviation":"DAL","city":"Dallas","conference":"West","division":"Southwest","full_name":"Dallas Mavericks","id":7,"name":"Mavericks"},"turnover":1},{"ast":8,"blk":0,"dreb":4,"fg3_pct":0.25,"fg3a":4,"fg3m":1,"fg_pct":0.538,"fga":13,"fgm":7,"ft_pct":1.0,"fta":5,"ftm":5,"game":{"date":"2021-11-21T00:00:00.000Z","home_team_id":13,"home_team_score":97,"id":473658,"period":4,"postseason":false,"season":2021,"status":"Final","time":"","visitor_team_id":7,"visitor_team_score":91},"id":8241218,"min":"35","oreb":0,"pf":4,"player":{"first_name":"Jalen","height_feet":6,"height_inches":3,"id":73,"last_name":"Brunson","position":"G","team_id":20,"weight_pounds":190},"pts":20,"reb":4,"stl":3,"team":{"abbreviation":"DAL","city":"Dallas","conference":"West","division":"Southwest","full_name":"Dallas Mavericks","id":7,"name":"Mavericks"},"turnover":3},{"ast":1,"blk":0,"dreb":5,"fg3_pct":0.0,"fg3a":2,"fg3m":0,"fg_pct":0.0,"fga":2,"fgm":0,"ft_pct":0.0,"fta":0,"ftm":0,"game":{"date":"2021-11-21T00:00:00.000Z","home_team_id":13,"home_team_score":97,"id":473658,"period":4,"postseason":false,"season":2021,"status":"Final","time":"","visitor_team_id":7,"visitor_team_score":91},"id":8241221,"min":"31:37","oreb":0,"pf":1,"player":{"first_name":"Reggie","height_feet":6,"height_inches":7,"id":75,"last_name":"Bullock","position":"G-F","team_id":7,"weight_pounds":205},"pts":0,"reb":5,"stl":0,"team":{"abbreviation":"DAL","city":"Dallas","conference":"West","division":"Southwest","full_name":"Dallas Mavericks","id":7,"name":"Mavericks"},"turnover":1},{"ast":1,"blk":0,"dreb":2,"fg3_pct":0.0,"fg3a":1,"fg3m":0,"fg_pct":0.0,"fga":1,"fgm":0,"ft_pct":0.0,"fta":0,"ftm":0,"game":{"date":"2021-11-21T00:00:00.000Z","home_team_id":13,"home_team_score":97,"id":473658,"period":4,"postseason":false,"season":2021,"status":"Final","time":"","visitor_team_id":7,"visitor_team_score":91},"id":8241220,"min":"7:37","oreb":0,"pf":1,"player":{"first_name":"Sterling","height_feet":6,"height_inches":6,"id":72,"last_name":"Brown","position":"G","team_id":14,"weight_pounds":232},"pts":0,"reb":2,"stl":0,"team":{"abbreviation":"DAL","city":"Dallas","conference":"West","division":"Southwest","full_name":"Dallas Mavericks","id":7,"name":"Mavericks"},"turnover":1},{"ast":0,"blk":0,"dreb":0,"fg3_pct":0.0,"fg3a":0,"fg3m":0,"fg_pct":0.0,"fga":0,"fgm":0,"ft_pct":0.0,"fta":0,"ftm":0,"game":{"date":"2021-11-21T00:00:00.000Z","home_team_id":13,"home_team_score":97,"id":473658,"period":4,"postseason":false,"season":2021,"status":"Final","time":"","visitor_team_id":7,"visitor_team_score":91},"id":8241219,"min":"0:00","oreb":0,"pf":0,"player":{"first_name":"Moses","id":666476,"last_name":"Brown","position":"C","team_id":3},"pts":0,"reb":0,"stl":0,"team":{"abbreviation":"DAL","city":"Dallas","conference":"West","division":"Southwest","full_name":"Dallas Mavericks","id":7,"name":"Mavericks"},"turnover":0},{"ast":1,"blk":0,"dreb":1,"fg3_pct":0.0,"fg3a":1,"fg3m":0,"fg_pct":0.333,"fga":6,"fgm":2,"fta":0,"ftm":0,"game":{"date":"2021-11-21T00:00:00.000Z","home_team_id":13,"home_team_score":97,"id":473658,"period":4,"postseason":false,"season":2021,"status":"Final","time":"","visitor_team_id":7,"visitor_team_score":91},"id":8241222,"min":"13","oreb":0,"pf":0,"player":{"first_name":"Trey","height_feet":6,"height_inches":1,"id":76,"last_name":"Burke","position":"G","team_id":21,"weight_pounds":175},"pts":4,"reb":1,"stl":0,"team":{"abbreviation":"DAL","city":"Dallas","conference":"West","division":"Southwest","full_name":"Dallas Mavericks","id":7,"name":"Mavericks"},"turnover":0},{"ast":0,"blk":0,"dreb":1,"fg3a":0,"fg3m":0,"fg_pct":1.0,"fga":2,"fgm":2,"fta":0,"ftm":0,"game":{"date":"2021-11-21T00:00:00.000Z","home_team_id":13,"home_team_score":97,"id":473658,"period":4,"postseason":false,"season":2021,"status":"Final","time":"","visitor_team_id":7,"visitor_team_score":91},"id":8241223,"min":"10","oreb":0,"pf":2,"player":{"first_name":"Willie","height_feet":7,"height_inches":0,"id":91,"last_name":"Cauley-Stein","position":"C","team_id":11,"weight_pounds":240},"pts":4,"reb":1,"stl":2,"team":{"abbreviation":"DAL","city":"Dallas","conference":"West","division":"Southwest","full_name":"Dallas Mavericks","id":7,"name":"Mavericks"},"turnover":2},{"ast":0,"blk":1,"dreb":3,"fg3_pct":0.2,"fg3a":5,"fg3m":1,"fg_pct":0.286,"fga":7,"fgm":2,"fta":0,"ftm":0,"game":{"date":"2021-11-21T00:00:00.000Z","home_team_id":13,"home_team_score":97,"id":473658,"period":4,"postseason":false,"season":2021,"status":"Final","time":"","visitor_team_id":7,"visitor_team_score":91},"id":8241225,"min":"20","oreb":1,"pf":0,"player":{"first_name":"Maxi","height_feet":6,"height_inches":11,"id":257,"last_name":"Kleber","position":"F","team_id":7,"weight_pounds":240},"pts":5,"reb":4,"stl":0,"team":{"abbreviation":"DAL","city":"Dallas","conference":"West","division":"Southwest","full_name":"Dallas Mavericks","id":7,"name":"Mavericks"},"turnover":0},{"ast":0,"blk":0,"dreb":1,"fg3a":0,"fg3m":0,"fg_pct":0.667,"fga":3,"fgm":2,"ft_pct":1.0,"fta":2,"ftm":2,"game":{"date":"2021-11-21T00:00:00.000Z","home_team_id":13,"home_team_score":97,"id":473658,"period":4,"postseason":false,"season":2021,"status":"Final","time":"","visitor_team_id":7,"visitor_team_score":91},"id":8241226,"min":"3","oreb":0,"pf":1,"player":{"first_name":"Boban","height_feet":7,"height_inches":3,"id":296,"last_name":"Marjanovic","position":"C","team_id":11,"weight_pounds":290},"pts":6,"reb":1,"stl":0,"team":{"abbreviation":"DAL","city":"Dallas","conference":"West","division":"Southwest","full_name":"Dallas Mavericks","id":7,"name":"Mavericks"},"turnover":0},{"ast":0,"blk":0,"dreb":0,"fg3_pct":0.0,"fg3a":0,"fg3m":0,"fg_pct":0.0,"fga":0,"fgm":0,"ft_pct":0.0,"fta":0,"ftm":0,"game":{"date":"2021-11-21T00:00:00.000Z","home_team_id":13,"home_team_score":97,"id":473658,"period":4,"postseason":false,"season":2021,"status":"Final","time":"","visitor_team_id":7,"visitor_team_score":91},"id":8241224,"min":"0:00","oreb":0,"pf":0,"player":{"first_name":"Josh","id":3547258,"last_name":"Green","position":"G","team_id":7},"pts":0,"reb":0,"stl":0,"team":{"abbreviation":"DAL","city":"Dallas","conference":"West","division":"Southwest","full_name":"Dallas Mavericks","id":7,"name":"Mavericks"},"turnover":0},{"ast":0,"blk":0,"dreb":0,"fg3_pct":0.0,"fg3a":0,"fg3m":0,"fg_pct":0.0,"fga":0,"fgm":0,"ft_pct":0.0,"fta":0,"ftm":0,"game":{"date":"2021-11-21T00:00:00.000Z","home_team_id":13,"home_team_score":97,"id":473658,"period":4,"postseason":false,"season":2021,"status":"Final","time":"","visitor_team_id":7,"visitor_team_score":91},"id":8241229,"min":"","oreb":0,"pf":0,"player":{"first_name":"Nicolas","height_feet":6,"height_inches":8,"id":33,"last_name":"Batum","position":"F-G","team_id":13,"weight_pounds":200},"pts":0,"reb":0,"stl":0,"team":{"abbreviation":"LAC","city":"LA","conference":"West","division":"Pacific","full_name":"LA Clippers","id":13,"name":"Clippers"},"turnover":0},{"ast":6,"blk":0,"dreb":4,"fg3_pct":0.375,"fg3a":8,"fg3m":3,"fg_pct":0.48,"fga":25,"fgm":12,"ft_pct":1.0,"fta":2,"ftm":2,"game":{"date":"2021-11-21T00:00:00.000Z","home_team_id":13,"home_team_score":97,"id":473658,"period":4,"postseason":false,"season":2021,"status":"Final","time":"","visitor_team_id":7,"visitor_team_score":91},"id":8241228,"min":"38","oreb":0,"pf":4,"player":{"first_name":"Paul","height_feet":6,"height_inches":9,"id":172,"last_name":"George","position":"F","team_id":13,"weight_pounds":220},"pts":29,"reb":4,"stl":1,"team":{"abbreviation":"LAC","city":"LA","conference":"West","division":"Pacific","full_name":"LA Clippers","id":13,"name":"Clippers"},"turnover":6},{"ast":2,"blk":0,"dreb":5,"fg3_pct":0.5,"fg3a":2,"fg3m":1,"fg_pct":0.5,"fga":2,"fgm":1,"fta":0,"ftm":0,"game":{"date":"2021-11-21T00:00:00.000Z","home_team_id":13,"home_team_score":97,"id":473658,"period":4,"postseason":false,"season":2021,"status":"Final","time":"","visitor_team_id":7,"visitor_team_score":91},"id":8241234,"min":"25","oreb":0,"pf":0,"player":{"first_name":"Amir","id":666511,"last_name":"Coffey","position":"G","team_id":13},"pts":3,"reb":5,"stl":0,"team":{"abbreviation":"LAC","city":"LA","conference":"West","division":"Pacific","full_name":"LA Clippers","id":13,"name":"Clippers"},"turnover":0},{"ast":0,"blk":0,"dreb":9,"fg3a":0,"fg3m":0,"fg_pct":0.857,"fga":7,"fgm":6,"ft_pct":0.667,"fta":6,"ftm":4,"game":{"date":"2021-11-21T00:00:00.000Z","home_team_id":13,"home_team_score":97,"id":473658,"period":4,"postseason":false,"season":2021,"status":"Final","time":"","visitor_team_id":7,"visitor_team_score":91},"id":8241230,"min":"27","oreb":1,"pf":1,"player":{"first_name":"Ivica","height_feet":7,"height_inches":1,"id":493,"last_name":"Zubac","position":"C","team_id":13,"weight_pounds":240},"pts":16,"reb":10,"stl":0,"team":{"abbreviation":"LAC","city":"LA","conference":"West","division":"Pacific","full_name":"LA Clippers","id":13,"name":"Clippers"},"turnover":1},{"ast":2,"blk":0,"dreb":4,"fg3_pct":0.0,"fg3a":1,"fg3m":0,"fg_pct":0.25,"fga":4,"fgm":1,"fta":0,"ftm":0,"game":{"date":"2021-11-21T00:00:00.000Z","home_team_id":13,"home_team_score":97,"id":473658,"period":4,"postseason":false,"season":2021,"status":"Final","time":"","visitor_team_id":7,"visitor_team_score":91},"id":8241231,"min":"26","oreb":0,"pf":2,"player":{"first_name":"Eric","height_feet":6,"height_inches":1,"id":51,"last_name":"Bledsoe","position":"G","team_id":25,"weight_pounds":205},"pts":2,"reb":4,"stl":0,"team":{"abbreviation":"LAC","city":"LA","conference":"West","division":"Pacific","full_name":"LA Clippers","id":13,"name":"Clippers"},"turnover":2},{"ast":4,"blk":0,"dreb":2,"fg3_pct":0.5,"fg3a":8,"fg3m":4,"fg_pct":0.571,"fga":14,"fgm":8,"ft_pct":0.75,"fta":4,"ftm":3,"game":{"date":"2021-11-21T00:00:00.000Z","home_team_id":13,"home_team_score":97,"id":473658,"period":4,"postseason":false,"season":2021,"status":"Final","time":"","visitor_team_id":7,"visitor_team_score":91},"id":8241232,"min":"35","oreb":0,"pf":2,"player":{"first_name":"Reggie","height_feet":6,"height_inches":3,"id":236,"last_name":"Jackson","position":"G","team_id":8,"weight_pounds":208},"pts":23,"reb":2,"stl":0,"team":{"abbreviation":"LAC","city":"LA","conference":"West","division":"Pacific","full_name":"LA Clippers","id":13,"name":"Clippers"},"turnover":2},{"ast":2,"blk":1,"dreb":2,"fg3_pct":0.429,"fg3a":7,"fg3m":3,"fg_pct":0.375,"fga":8,"fgm":3,"fta":0,"ftm":0,"game":{"date":"2021-11-21T00:00:00.000Z","home_team_id":13,"home_team_score":97,"id":473658,"period":4,"postseason":false,"season":2021,"status":"Final","time":"","visitor_team_id":7,"visitor_team_score":91},"id":8241237,"min":"34","oreb":1,"pf":2,"player":{"first_name":"Luke","height_feet":6,"height_inches":5,"id":254,"last_name":"Kennard","position":"G","team_id":15,"weight_pounds":206},"pts":9,"reb":3,"stl":2,"team":{"abbreviation":"LAC","city":"LA","conference":"West","division":"Pacific","full_name":"LA Clippers","id":13,"name":"Clippers"},"turnover":1},{"ast":0,"blk":0,"dreb":0,"fg3_pct":0.0,"fg3a":0,"fg3m":0,"fg_pct":0.0,"fga":0,"fgm":0,"ft_pct":0.0,"fta":0,"ftm":0,"game":{"date":"2021-11-21T00:00:00.000Z","home_team_id":13,"home_team_score":97,"id":473658,"period":4,"postseason":false,"season":2021,"status":"Final","time":"","visitor_team_id":7,"visitor_team_score":91},"id":8241233,"min":"0:00","oreb":0,"pf":0,"player":{"first_name":"Brandon","id":17896022,"last_name":"Boston Jr.","position":"G","team_id":13},"pts":0,"reb":0,"stl":0,"team":{"abbreviation":"LAC","city":"LA","conference":"West","division":"Pacific","full_name":"LA Clippers","id":13,"name":"Clippers"},"turnover":0},{"ast":0,"blk":0,"dreb":0,"fg3_pct":0.0,"fg3a":0,"fg3m":0,"fg_pct":0.0,"fga":0,"fgm":0,"ft_pct":0.0,"fta":0,"ftm":0,"game":{"date":"2021-11-21T00:00:00.000Z","home_team_id":13,"home_team_score":97,"id":473658,"period":4,"postseason":false,"season":2021,"status":"Final","time":"","visitor_team_id":7,"visitor_team_score":91},"id":8241239,"min":"0:00","oreb":0,"pf":0,"player":{"first_name":"Jay","id":3547280,"last_name":"Scrubb","position":"G","team_id":22},"pts":0,"reb":0,"stl":0,"team":{"abbreviation":"LAC","city":"LA","conference":"West","division":"Pacific","full_name":"LA Clippers","id":13,"name":"Clippers"},"turnover":0},{"ast":0,"blk":0,"dreb":2,"fg3_pct":0.0,"fg3a":2,"fg3m":0,"fg_pct":0.25,"fga":8,"fgm":2,"ft_pct":0.5,"fta":4,"ftm":2,"game":{"date":"2021-11-21T00:00:00.000Z","home_team_id":13,"home_team_score":97,"id":473658,"period":4,"postseason":false,"season":2021,"status":"Final","time":"","visitor_team_id":7,"visitor_team_score":91},"id":8241236,"min":"12","oreb":2,"pf":2,"player":{"first_name":"Serge","height_feet":6,"height_inches":10,"id":223,"last_name":"Ibaka","position":"F-C","team_id":17,"weight_pounds":235},"pts":6,"reb":4,"stl":1,"team":{"abbreviation":"LAC","city":"LA","conference":"West","division":"Pacific","full_name":"LA Clippers","id":13,"name":"Clippers"},"turnover":2},{"ast":0,"blk":0,"dreb":3,"fg3_pct":1.0,"fg3a":1,"fg3m":1,"fg_pct":0.5,"fga":4,"fgm":2,"ft_pct":1.0,"fta":2,"ftm":2,"game":{"date":"2021-11-21T00:00:00.000Z","home_team_id":13,"home_team_score":97,"id":473658,"period":4,"postseason":false,"season":2021,"status":"Final","time":"","visitor_team_id":7,"visitor_team_score":91},"id":8241238,"min":"27","oreb":1,"pf":2,"player":{"first_name":"Terance","id":666743,"last_name":"Mann","position":"G","team_id":13},"pts":7,"reb":4,"stl":0,"team":{"abbreviation":"LAC","city":"LA","conference":"West","division":"Pacific","full_name":"LA Clippers","id":13,"name":"Clippers"},"turnover":0},{"ast":1,"blk":0,"dreb":3,"fg3_pct":0.0,"fg3a":0,"fg3m":0,"fg_pct":0.0,"fga":0,"fgm":0,"ft_pct":0.0,"fta":0,"ftm":0,"game":{"date":"2021-11-21T00:00:00.000Z","home_team_id":13,"home_team_score":97,"id":473658,"period":4,"postseason":false,"season":2021,"status":"Final","time":"","visitor_team_id":7,"visitor_team_score":91},"id":8241240,"min":"10:12","oreb":1,"pf":0,"player":{"first_name":"Justise","height_feet":6,"height_inches":7,"id":485,"last_name":"Winslow","position":"F","team_id":25,"weight_pounds":225},"pts":0,"reb":4,"stl":0,"team":{"abbreviation":"LAC","city":"LA","conference":"West","division":"Pacific","full_name":"LA Clippers","id":13,"name":"Clippers"},"turnover":0},{"ast":1,"blk":1,"dreb":0,"fg3a":0,"fg3m":0,"fg_pct":0.333,"fga":3,"fgm":1,"fta":0,"ftm":0,"game":{"date":"2021-11-21T00:00:00.000Z","home_team_id":13,"home_team_score":97,"id":473658,"period":4,"postseason":false,"season":2021,"status":"Final","time":"","visitor_team_id":7,"visitor_team_score":91},"id":8241235,"min":"5","oreb":2,"pf":0,"player":{"first_name":"Isaiah","height_feet":7,"height_inches":0,"id":201,"last_name":"Hartenstein","position":"F-C","team_id":20,"weight_pounds":249},"pts":2,"reb":2,"stl":1,"team":{"abbreviation":"LAC","city":"LA","conference":"West","division":"Pacific","full_name":"LA Clippers","id":13,"name":"Clippers"},"turnover":0},{"ast":1,"blk":1,"dreb":0,"fg3_pct":0.25,"fg3a":4,"fg3m":1,"fg_pct":0.167,"fga":6,"fgm":1,"fta":0,"ftm":0,"game":{"date":"2021-11-21T00:00:00.000Z","home_team_id":13,"home_team_score":97,"id":473658,"period":4,"postseason":false,"season":2021,"status":"Final","time":"","visitor_team_id":7,"visitor_team_score":91},"id":8241227,"min":"9","oreb":0,"pf":0,"player":{"first_name":"Frank","height_feet":6,"height_inches":6,"id":347,"last_name":"Ntilikina","position":"G","team_id":7,"weight_pounds":200},"pts":3,"reb":0,"stl":0,"team":{"abbreviation":"DAL","city":"Dallas","conference":"West","division":"Southwest","full_name":"Dallas Mavericks","id":7,"name":"Mavericks"},"turnover":1},{"ast":1,"blk":2,"dreb":2,"fg3a":0,"fg3m":0,"fg_pct":1.0,"fga":3,"fgm":3,"ft_pct":0.0,"fta":1,"ftm":0,"game":{"date":"2021-11-28T00:00:00.000Z","home_team_id":13,"home_team_score":90,"id":473709,"period":4,"postseason":false,"season":2021,"status":"Final","time":"","visitor_team_id":10,"visitor_team_score":105},"id":8431615,"min":"12","oreb":3,"pf":2,"player":{"first_name":"Isaiah","height_feet":7,"height_inches":0,"id":201,"last_name":"Hartenstein","position":"F-C","team_id":20,"weight_pounds":249},"pts":6,"reb":5,"stl":1,"team":{"abbreviation":"LAC","city":"LA","conference":"West","division":"Pacific","full_name":"LA Clippers","id":13,"name":"Clippers"},"turnover":1},{"ast":0,"blk":0,"dreb":2,"fg3a":0,"fg3m":0,"fg_pct":0.5,"fga":2,"fgm":1,"fta":0,"ftm":0,"game":{"date":"2021-11-28T00:00:00.000Z","home_team_id":13,"home_team_score":90,"id":473709,"period":4,"postseason":false,"season":2021,"status":"Final","time":"","visitor_team_id":10,"visitor_team_score":105},"id":8431614,"min":"10","oreb":0,"pf":1,"player":{"first_name":"Amir","id":666511,"last_name":"Coffey","position":"G","team_id":13},"pts":2,"reb":2,"stl":0,"team":{"abbreviation":"LAC","city":"LA","conference":"West","division":"Pacific","full_name":"LA Clippers","id":13,"name":"Clippers"},"turnover":0},{"ast":2,"blk":2,"dreb":5,"fg3_pct":0.4,"fg3a":5,"fg3m":2,"fg_pct":0.333,"fga":12,"fgm":4,"ft_pct":0.333,"fta":6,"ftm":2,"game":{"date":"2021-11-28T00:00:00.000Z","home_team_id":13,"home_team_score":90,"id":473709,"period":4,"postseason":false,"season":2021,"status":"Final","time":"","visitor_team_id":10,"visitor_team_score":105},"id":8431597,"min":"36","oreb":2,"pf":1,"player":{"first_name":"Andrew","height_feet":6,"height_inches":8,"id":475,"last_name":"Wiggins","position":"F-G","team_id":10,"weight_pounds":194},"pts":12,"reb":7,"stl":1,"team":{"abbreviation":"GSW","city":"Golden State","conference":"West","division":"Pacific","full_name":"Golden State Warriors","id":10,"name":"Warriors"},"turnover":2},{"ast":1,"blk":0,"dreb":1,"fg3a":0,"fg3m":0,"fg_pct":1.0,"fga":1,"fgm":1,"ft_pct":0.0,"fta":1,"ftm":0,"game":{"date":"2021-11-28T00:00:00.000Z","home_team_id":13,"home_team_score":90,"id":473709,"period":4,"postseason":false,"season":2021,"status":"Final","time":"","visitor_team_id":10,"visitor_team_score":105},"id":8431599,"min":"14","oreb":2,"pf":2,"player":{"first_name":"Kevon","height_feet":6,"height_inches":9,"id":282,"last_name":"Looney","position":"F","team_id":10,"weight_pounds":220},"pts":2,"reb":3,"stl":2,"team":{"abbreviation":"GSW","city":"Golden State","conference":"West","division":"Pacific","full_name":"Golden State Warriors","id":10,"name":"Warriors"},"turnover":2},{"ast":2,"blk":0,"dreb":3,"fg3_pct":0.4,"fg3a":10,"fg3m":4,"fg_pct":0.375,"fga":16,"fgm":6,"ft_pct":1.0,"fta":1,"ftm":1,"game":{"date":"2021-11-28T00:00:00.000Z","home_team_id":13,"home_team_score":90,"id":473709,"period":4,"postseason":false,"season":2021,"status":"Final","time":"","visitor_team_id":10,"visitor_team_score":105},"id":8431600,"min":"31","oreb":0,"pf":2,"player":{"first_name":"Jordan","id":666848,"last_name":"Poole","position":"G","team_id":10},"pts":17,"reb":3,"stl":1,"team":{"abbreviation":"GSW","city":"Golden State","conference":"West","division":"Pacific","full_name":"Golden State Warriors","id":10,"name":"Warriors"},"turnover":0},{"ast":6,"blk":0,"dreb":5,"fg3_pct":0.538,"fg3a":13,"fg3m":7,"fg_pct":0.545,"fga":22,"fgm":12,"ft_pct":1.0,"fta":2,"ftm":2,"game":{"date":"2021-11-28T00:00:00.000Z","home_team_id":13,"home_team_score":90,"id":473709,"period":4,"postseason":false,"season":2021,"status":"Final","time":"","visitor_team_id":10,"visitor_team_score":105},"id":8431601,"min":"35","oreb":0,"pf":4,"player":{"first_name":"Stephen","height_feet":6,"height_inches":3,"id":115,"last_name":"Curry","position":"G","team_id":10,"weight_pounds":190},"pts":33,"reb":5,"stl":6,"team":{"abbreviation":"GSW","city":"Golden State","conference":"West","division":"Pacific","full_name":"Golden State Warriors","id":10,"name":"Warriors"},"turnover":3},{"ast":1,"blk":0,"dreb":2,"fg3_pct":0.0,"fg3a":2,"fg3m":0,"fg_pct":0.333,"fga":6,"fgm":2,"fta":0,"ftm":0,"game":{"date":"2021-11-28T00:00:00.000Z","home_team_id":13,"home_team_score":90,"id":473709,"period":4,"postseason":false,"season":2021,"status":"Final","time":"","visitor_team_id":10,"visitor_team_score":105},"id":8431606,"min":"12","oreb":2,"pf":2,"player":{"first_name":"Gary","id":2189,"last_name":"Payton II","position":"","team_id":10},"pts":4,"reb":4,"stl":4,"team":{"abbreviation":"GSW","city":"Golden State","conference":"West","division":"Pacific","full_name":"Golden State Warriors","id":10,"name":"Warriors"},"turnover":1},{"ast":3,"blk":0,"dreb":3,"fg3_pct":0.5,"fg3a":2,"fg3m":1,"fg_pct":0.2,"fga":5,"fgm":1,"ft_pct":0.833,"fta":6,"ftm":5,"game":{"date":"2021-11-28T00:00:00.000Z","home_team_id":13,"home_team_score":90,"id":473709,"period":4,"postseason":false,"season":2021,"status":"Final","time":"","visitor_team_id":10,"visitor_team_score":105},"id":8431618,"min":"26","oreb":2,"pf":1,"player":{"first_name":"Terance","id":666743,"last_name":"Mann","position":"G","team_id":13},"pts":8,"reb":5,"stl":2,"team":{"abbreviation":"LAC","city":"LA","conference":"West","division":"Pacific","full_name":"LA Clippers","id":13,"name":"Clippers"},"turnover":4},{"ast":1,"blk":0,"dreb":0,"fg3a":0,"fg3m":0,"fg_pct":0.5,"fga":2,"fgm":1,"ft_pct":0.5,"fta":2,"ftm":1,"game":{"date":"2021-11-28T00:00:00.000Z","home_team_id":13,"home_team_score":90,"id":473709,"period":4,"postseason":false,"season":2021,"status":"Final","time":"","visitor_team_id":10,"visitor_team_score":105},"id":8431619,"min":"4","oreb":0,"pf":0,"player":{"first_name":"Justise","height_feet":6,"height_inches":7,"id":485,"last_name":"Winslow","position":"F","team_id":25,"weight_pounds":225},"pts":3,"reb":0,"stl":0,"team":{"abbreviation":"LAC","city":"LA","conference":"West","division":"Pacific","full_name":"LA Clippers","id":13,"name":"Clippers"},"turnover":0},{"ast":2,"blk":0,"dreb":8,"fg3_pct":0.429,"fg3a":7,"fg3m":3,"fg_pct":0.5,"fga":10,"fgm":5,"ft_pct":0.625,"fta":8,"ftm":5,"game":{"date":"2021-11-28T00:00:00.000Z","home_team_id":13,"home_team_score":90,"id":473709,"period":4,"postseason":false,"season":2021,"status":"Final","time":"","visitor_team_id":10,"visitor_team_score":105},"id":8431607,"min":"26","oreb":2,"pf":2,"player":{"first_name":"Otto","height_feet":6,"height_inches":8,"id":376,"last_name":"Porter Jr.","position":"F","team_id":28,"weight_pounds":198},"pts":18,"reb":10,"stl":2,"team":{"abbreviation":"GSW","city":"Golden State","conference":"West","division":"Pacific","full_name":"Golden State Warriors","id":10,"name":"Warriors"},"turnover":1},{"ast":1,"blk":0,"dreb":1,"fg3a":0,"fg3m":0,"fg_pct":0.5,"fga":2,"fgm":1,"fta":0,"ftm":0,"game":{"date":"2021-11-28T00:00:00.000Z","home_team_id":13,"home_team_score":90,"id":473709,"period":4,"postseason":false,"season":2021,"status":"Final","time":"","visitor_team_id":10,"visitor_team_score":105},"id":8431602,"min":"12","oreb":1,"pf":3,"player":{"first_name":"Nemanja","height_feet":6,"height_inches":10,"id":49,"last_name":"Bjelica","position":"F","team_id":10,"weight_pounds":234},"pts":2,"reb":2,"stl":0,"team":{"abbreviation":"GSW","city":"Golden State","conference":"West","division":"Pacific","full_name":"Golden State Warriors","id":10,"name":"Warriors"},"turnover":1},{"ast":2,"blk":0,"dreb":0,"fg3_pct":0.0,"fg3a":1,"fg3m":0,"fg_pct":0.5,"fga":4,"fgm":2,"fta":0,"ftm":0,"game":{"date":"2021-11-28T00:00:00.000Z","home_team_id":13,"home_team_score":90,"id":473709,"period":4,"postseason":false,"season":2021,"status":"Final","time":"","visitor_team_id":10,"visitor_team_score":105},"id":8431608,"min":"22","oreb":0,"pf":3,"player":{"first_name":"Juan","id":666925,"last_name":"Toscano-Anderson","position":"F","team_id":29},"pts":4,"reb":0,"stl":1,"team":{"abbreviation":"GSW","city":"Golden State","conference":"West","division":"Pacific","full_name":"Golden State Warriors","id":10,"name":"Warriors"},"turnover":1},{"ast":0,"blk":0,"dreb":2,"fg3_pct":1.0,"fg3a":1,"fg3m":1,"fg_pct":1.0,"fga":2,"fgm":2,"fta":0,"ftm":0,"game":{"date":"2021-11-28T00:00:00.000Z","home_team_id":13,"home_team_score":90,"id":473709,"period":4,"postseason":false,"season":2021,"status":"Final","time":"","visitor_team_id":10,"visitor_team_score":105},"id":8431604,"min":"3","oreb":0,"pf":0,"player":{"first_name":"Jonathan","id":17553979,"last_name":"Kuminga","position":"F","team_id":10},"pts":5,"reb":2,"stl":0,"team":{"abbreviation":"GSW","city":"Golden State","conference":"West","division":"Pacific","full_name":"Golden State Warriors","id":10,"name":"Warriors"},"turnover":0},{"ast":1,"blk":0,"dreb":1,"fg3_pct":0.0,"fg3a":1,"fg3m":0,"fg_pct":0.0,"fga":3,"fgm":0,"ft_pct":0.0,"fta":0,"ftm":0,"game":{"date":"2021-11-28T00:00:00.000Z","home_team_id":13,"home_team_score":90,"id":473709,"period":4,"postseason":false,"season":2021,"status":"Final","time":"","visitor_team_id":10,"visitor_team_score":105},"id":8431603,"min":"18:31","oreb":2,"pf":4,"player":{"first_name":"Chris","id":50661,"last_name":"Chiozza","position":"G","team_id":10},"pts":0,"reb":3,"stl":0,"team":{"abbreviation":"GSW","city":"Golden State","conference":"West","division":"Pacific","full_name":"Golden State Warriors","id":10,"name":"Warriors"},"turnover":1},{"ast":0,"blk":0,"dreb":0,"fg3_pct":0.0,"fg3a":0,"fg3m":0,"fg_pct":0.0,"fga":1,"fgm":0,"ft_pct":0.0,"fta":0,"ftm":0,"game":{"date":"2021-11-28T00:00:00.000Z","home_team_id":13,"home_team_score":90,"id":473709,"period":4,"postseason":false,"season":2021,"status":"Final","time":"","visitor_team_id":10,"visitor_team_score":105},"id":8431605,"min":"2:32","oreb":0,"pf":0,"player":{"first_name":"Moses","id":17553992,"last_name":"Moody","position":"G","team_id":10},"pts":0,"reb":0,"stl":0,"team":{"abbreviation":"GSW","city":"Golden State","conference":"West","division":"Pacific","full_name":"Golden State Warriors","id":10,"name":"Warriors"},"turnover":0},{"ast":5,"blk":0,"dreb":5,"fg3_pct":0.429,"fg3a":7,"fg3m":3,"fg_pct":0.458,"fga":24,"fgm":11,"ft_pct":0.833,"fta":6,"ftm":5,"game":{"date":"2021-11-28T00:00:00.000Z","home_team_id":13,"home_team_score":90,"id":473709,"period":4,"postseason":false,"season":2021,"status":"Final","time":"","visitor_team_id":10,"visitor_team_score":105},"id":8431609,"min":"37","oreb":0,"pf":3,"player":{"first_name":"Paul","height_feet":6,"height_inches":9,"id":172,"last_name":"George","position":"F","team_id":13,"weight_pounds":220},"pts":30,"reb":5,"stl":0,"team":{"abbreviation":"LAC","city":"LA","conference":"West","division":"Pacific","full_name":"LA Clippers","id":13,"name":"Clippers"},"turnover":8},{"ast":5,"blk":0,"dreb":4,"fg3_pct":0.4,"fg3a":5,"fg3m":2,"fg_pct":0.385,"fga":13,"fgm":5,"ft_pct":1.0,"fta":1,"ftm":1,"game":{"date":"2021-11-28T00:00:00.000Z","home_team_id":13,"home_team_score":90,"id":473709,"period":4,"postseason":false,"season":2021,"status":"Final","time":"","visitor_team_id":10,"visitor_team_score":105},"id":8431610,"min":"34","oreb":2,"pf":4,"player":{"first_name":"Marcus","height_feet":6,"height_inches":9,"id":328,"last_name":"Morris","position":"F","team_id":13,"weight_pounds":235},"pts":13,"reb":6,"stl":0,"team":{"abbreviation":"LAC","city":"LA","conference":"West","division":"Pacific","full_name":"LA Clippers","id":13,"name":"Clippers"},"turnover":2},{"ast":1,"blk":0,"dreb":4,"fg3a":0,"fg3m":0,"fg_pct":0.6,"fga":5,"fgm":3,"ft_pct":0.5,"fta":4,"ftm":2,"game":{"date":"2021-11-28T00:00:00.000Z","home_team_id":13,"home_team_score":90,"id":473709,"period":4,"postseason":false,"season":2021,"status":"Final","time":"","visitor_team_id":10,"visitor_team_score":105},"id":8431611,"min":"21","oreb":4,"pf":2,"player":{"first_name":"Ivica","height_feet":7,"height_inches":1,"id":493,"last_name":"Zubac","position":"C","team_id":13,"weight_pounds":240},"pts":8,"reb":8,"stl":1,"team":{"abbreviation":"LAC","city":"LA","conference":"West","division":"Pacific","full_name":"LA Clippers","id":13,"name":"Clippers"},"turnover":1},{"ast":0,"blk":1,"dreb":6,"fg3_pct":0.5,"fg3a":4,"fg3m":2,"fg_pct":0.444,"fga":9,"fgm":4,"ft_pct":0.75,"fta":4,"ftm":3,"game":{"date":"2021-11-28T00:00:00.000Z","home_team_id":13,"home_team_score":90,"id":473709,"period":4,"postseason":false,"season":2021,"status":"Final","time":"","visitor_team_id":10,"visitor_team_score":105},"id":8431612,"min":"33","oreb":4,"pf":1,"player":{"first_name":"Eric","height_feet":6,"height_inches":1,"id":51,"last_name":"Bledsoe","position":"G","team_id":25,"weight_pounds":205},"pts":13,"reb":10,"stl":0,"team":{"abbreviation":"LAC","city":"LA","conference":"West","division":"Pacific","full_name":"LA Clippers","id":13,"name":"Clippers"},"turnover":1},{"ast":2,"blk":0,"dreb":1,"fg3_pct":0.0,"fg3a":3,"fg3m":0,"fg_pct":0.0,"fga":5,"fgm":0,"ft_pct":0.0,"fta":1,"ftm":0,"game":{"date":"2021-11-28T00:00:00.000Z","home_team_id":13,"home_team_score":90,"id":473709,"period":4,"postseason":false,"season":2021,"status":"Final","time":"","visitor_team_id":10,"visitor_team_score":105},"id":8431613,"min":"21:14","oreb":0,"pf":4,"player":{"first_name":"Reggie","height_feet":6,"height_inches":3,"id":236,"last_name":"Jackson","position":"G","team_id":8,"weight_pounds":208},"pts":0,"reb":1,"stl":2,"team":{"abbreviation":"LAC","city":"LA","conference":"West","division":"Pacific","full_name":"LA Clippers","id":13,"name":"Clippers"},"turnover":3},{"ast":0,"blk":0,"dreb":2,"fg3_pct":0.2,"fg3a":5,"fg3m":1,"fg_pct":0.25,"fga":8,"fgm":2,"fta":0,"ftm":0,"game":{"date":"2021-11-28T00:00:00.000Z","home_team_id":13,"home_team_score":90,"id":473709,"period":4,"postseason":false,"season":2021,"status":"Final","time":"","visitor_team_id":10,"visitor_team_score":105},"id":8431617,"min":"34","oreb":0,"pf":2,"player":{"first_name":"Luke","height_feet":6,"height_inches":5,"id":254,"last_name":"Kennard","position":"G","team_id":15,"weight_pounds":206},"pts":5,"reb":2,"stl":2,"team":{"abbreviation":"LAC","city":"LA","conference":"West","division":"Pacific","full_name":"LA Clippers","id":13,"name":"Clippers"},"turnover":3},{"ast":0,"blk":0,"dreb":3,"fg3_pct":0.0,"fg3a":2,"fg3m":0,"fg_pct":0.25,"fga":4,"fgm":1,"fta":0,"ftm":0,"game":{"date":"2021-11-28T00:00:00.000Z","home_team_id":13,"home_team_score":90,"id":473709,"period":4,"postseason":false,"season":2021,"status":"Final","time":"","visitor_team_id":10,"visitor_team_score":105},"id":8431616,"min":"9","oreb":0,"pf":1,"player":{"first_name":"Serge","height_feet":6,"height_inches":10,"id":223,"last_name":"Ibaka","position":"F-C","team_id":17,"weight_pounds":235},"pts":2,"reb":3,"stl":0,"team":{"abbreviation":"LAC","city":"LA","conference":"West","division":"Pacific","full_name":"LA Clippers","id":13,"name":"Clippers"},"turnover":1},{"ast":7,"blk":0,"dreb":4,"fg3a":0,"fg3m":0,"fg_pct":0.429,"fga":7,"fgm":3,"ft_pct":0.5,"fta":4,"ftm":2,"game":{"date":"2021-11-28T00:00:00.000Z","home_team_id":13,"home_team_score":90,"id":473709,"period":4,"postseason":false,"season":2021,"status":"Final","time":"","visitor_team_id":10,"visitor_team_score":105},"id":8431598,"min":"30","oreb":0,"pf":4,"player":{"first_name":"Draymond","height_feet":6,"height_inches":7,"id":185,"last_name":"Green","position":"F","team_id":10,"weight_pounds":230},"pts":8,"reb":4,"stl":2,"team":{"abbreviation":"GSW","city":"Golden State","conference":"West","division":"Pacific","full_name":"Golden State Warriors","id":10,"name":"Warriors"},"turnover":4}],"meta":{"current_page":1,"per_page":100,"total_count":72,"total_pages":1}}
